secenv/__init__.py
secenv/config.py
secenv/context.py
secenv/secrets.py
secenv/store.py
secenv/stores/__init__.py
secenv/stores/akeyless.py
secenv/stores/aws.py
secenv/stores/azure.py
secenv/stores/bitwarden.py
secenv/stores/env.py
secenv/stores/gcp.py
secenv/stores/pass.py
secenv/stores/scaleway.py
secenv/stores/vault.py
secenv/utils.py
secenv-2.1.2.dist-info/LICENSE
secenv-2.1.2.dist-info/METADATA
secenv-2.1.2.dist-info/WHEEL
secenv-2.1.2.dist-info/entry_points.txt
secenv-2.1.2.dist-info/RECORD
