Metadata-Version: 2.1
Name: secenv
Version: 2.1.2
Summary: An utility tool to list, read and fill secrets from multiple stores.
License: GPL-3.0-or-later
Author: Keltio Labs
Author-email: labs@keltio.fr
Requires-Python: >=3.8,<4.0
Classifier: License :: OSI Approved :: GNU General Public License v3 or later (GPLv3+)
Classifier: Programming Language :: Python :: 3
Classifier: Programming Language :: Python :: 3.8
Classifier: Programming Language :: Python :: 3.9
Classifier: Programming Language :: Python :: 3.10
Classifier: Programming Language :: Python :: 3.11
Classifier: Programming Language :: Python :: 3.12
Requires-Dist: akeyless (>=3.5.0,<4.0.0)
Requires-Dist: azure-identity (>=1.15.0,<2.0.0)
Requires-Dist: azure-keyvault-secrets (>=4.7.0,<5.0.0)
Requires-Dist: boto3 (>=1.33.4,<2.0.0)
Requires-Dist: google-cloud-secret-manager (>=2.16.4,<3.0.0)
Requires-Dist: hvac (>=2.0.0,<3.0.0)
Requires-Dist: passpy (>=1.0.2,<2.0.0)
Requires-Dist: pyyaml (>=6.0.1,<7.0.0)
